example/__init__.py
example/hello.py
Example_Python_Package-1.0.3.dist-info/METADATA
Example_Python_Package-1.0.3.dist-info/WHEEL
Example_Python_Package-1.0.3.dist-info/top_level.txt
Example_Python_Package-1.0.3.dist-info/RECORD
