Metadata-Version: 2.1
Name: Example-Python-Package
Version: 1.0.3
Summary: An example Python package
Home-page: https://example.com
Author: matcaz
Author-email: UNKNOWN
License: UNKNOWN
Platform: UNKNOWN
